tonal/__init__.py
tonal/chords.py
tonal/chordspace.py
tonal/converters.py
tonal/counterpoint.py
tonal/notes.py
tonal/util.py
tonal/data/Caeds Small Trash GM v1.06.sf2
tonal/scrap/extract_chords_and_lyrics.py
tonal/tests/__init__.py
tonal/tests/test_chords.py
tonal/tests/test_chordspace.py
tonal/tests/test_notes.py
tonal-0.0.16.dist-info/METADATA
tonal-0.0.16.dist-info/WHEEL
tonal-0.0.16.dist-info/licenses/LICENSE
tonal-0.0.16.dist-info/RECORD
