Metadata-Version: 2.4
Name: tonal
Version: 0.0.16
Summary: Tools for music analysis and generation
Project-URL: Homepage, https://github.com/thorwhalen/tonal
Author: Thor Whalen
License: MIT
License-File: LICENSE
Requires-Python: >=3.10
Requires-Dist: lkj
Requires-Dist: mido
Requires-Dist: music21
Requires-Dist: numpy
Provides-Extra: dev
Requires-Dist: pytest-cov>=4.0; extra == 'dev'
Requires-Dist: pytest>=7.0; extra == 'dev'
Requires-Dist: ruff>=0.1.0; extra == 'dev'
Provides-Extra: docs
Requires-Dist: sphinx-rtd-theme>=1.0; extra == 'docs'
Requires-Dist: sphinx>=6.0; extra == 'docs'
